pycolorit/__init__.py
pycolorit/_data.py
pycolorit/color.py
pycolorit/conversion.py
pycolorit/css_filter.py
pycolorit/data.py
pycolorit/exception.py
pycolorit/gradient.py
pycolorit/number.py
pycolorit/_data/README.md
pycolorit/_data/css-named-colors.json
pycolorit-0.1.1.dist-info/METADATA
pycolorit-0.1.1.dist-info/WHEEL
pycolorit-0.1.1.dist-info/top_level.txt
pycolorit-0.1.1.dist-info/RECORD
