Metadata-Version: 2.2
Name: PyColorIT
Version: 0.1.1
Requires-Python: >=3.10
Requires-Dist: numpy
Requires-Dist: PkgData<0.2,>=0.1
Requires-Dist: ipython
